{"inkVersion":21,"root":[["^А ты неплохо справляешься. ","#","^speaker:Пак ","/#","#","^portrait:pak_neutral ","/#","#","^layout:right","/#","\n","^Я думала ты побежишь домой после первой стычки.","\n","^Ты, вроде, отправилась со мной, чтобы помогать. ","#","^speaker:Йоко ","/#","#","^portrait:yohko_neutral ","/#","#","^layout:left","/#","\n","^Может начнешь уже быть полезной?","\n","^Ладно, извини, просто я хочу чтобы ты воспринимала это задание серьезней.  ","#","^speaker:Пак ","/#","#","^portrait:pak_sad ","/#","#","^layout:right","/#","\n","^Гоблины действительно слабы, но кто знает чем это может обернуться.","\n","^Поговаривают, что где-то в этой местности есть тайный выход, который охраняет дракон.","\n","^Если ты решишь сразиться с ним, то сперва нужно как следует подготовиться и поискать полезные предметы в округе.","\n","end",["done",{"#f":5,"#n":"g-0"}],null],"done",{"#f":1}],"listDefs":{}}